proxyrotator/__init__.py
proxyrotator/proxyrotator.py
proxyrotator-0.0.2.dist-info/METADATA
proxyrotator-0.0.2.dist-info/WHEEL
proxyrotator-0.0.2.dist-info/top_level.txt
proxyrotator-0.0.2.dist-info/RECORD
