Metadata-Version: 2.1
Name: proxyrotator
Version: 0.0.2
Summary: A simple proxy rotation utility
Home-page: UNKNOWN
Author: M Vashishta Varma
Author-email: levovarma@gmail.com
License: UNKNOWN
Platform: UNKNOWN
Classifier: Programming Language :: Python :: 3
Classifier: License :: OSI Approved :: MIT License
Classifier: Operating System :: OS Independent
Requires-Python: >=3.6
Requires-Dist: requests
